README.md
setup.py
Deepcell_Data_Processing.egg-info/PKG-INFO
Deepcell_Data_Processing.egg-info/SOURCES.txt
Deepcell_Data_Processing.egg-info/dependency_links.txt
Deepcell_Data_Processing.egg-info/requires.txt
Deepcell_Data_Processing.egg-info/top_level.txt
deepcell_data_processing/__init__.py
deepcell_data_processing/processing.py
deepcell_data_processing/processing_test.py
deepcell_data_processing/retinanet.py
deepcell_data_processing/retinanet_test.py