Metadata-Version: 2.1
Name: Deepcell-Data-Processing
Version: 0.1.0
Summary: The pre- and post-processing functions module for deepcell-tf.
Home-page: https://github.com/vanvalenlab/deepcell-data-processing
Author: Van Valen Lab
Author-email: vanvalenlab@gmail.com
License: LICENSE
Download-URL: https://github.com/vanvalenlab/deepcell-data-processing/tarball/0.1.0
Platform: UNKNOWN
Provides-Extra: tests
